cgecore-2.0.1.dist-info/METADATA
cgecore-2.0.1.dist-info/WHEEL
cgecore-2.0.1.dist-info/entry_points.txt
cgecore-2.0.1.dist-info/licenses/LICENSE.txt
cgecore/__init__.py
cgecore/alignment.py
cgecore/alignment/KMA/README.md
cgecore/alignment/KMA/__init__.py
cgecore/alignment/KMA/alignment_files.md
cgecore/alignment/KMA/alignment_files.py
cgecore/alignment/KMA/read_files.md
cgecore/alignment/KMA/read_files.py
cgecore/alignment/README.md
cgecore/alignment/__init__.py
cgecore/alignment/aligner.md
cgecore/alignment/aligner.py
cgecore/alignment/blast/README.md
cgecore/alignment/blast/__init__.py
cgecore/alignment/blast/alignment_files.md
cgecore/alignment/blast/alignment_files.py
cgecore/alignment/blast/read_files.md
cgecore/alignment/blast/read_files.py
cgecore/alignment/read_alignment.md
cgecore/alignment/read_alignment.py
cgecore/alignment/scheme_submodule.png
cgecore/applications/Blast.md
cgecore/applications/Blast.py
cgecore/applications/KMA.md
cgecore/applications/KMA.py
cgecore/applications/README.md
cgecore/applications/__init__.py
cgecore/applications/command.md
cgecore/applications/command.py
cgecore/argumentparsing.py
cgecore/blaster/__init__.py
cgecore/blaster/blaster.py
cgecore/blaster/known_issues.txt
cgecore/blaster/run_blaster.py
cgecore/blaster/tests/data/test_db_01.fsa
cgecore/blaster/tests/data/test_isolate_01.fa
cgecore/blaster/tests/functional_tests.py
cgecore/blaster/tests/unit_tests.py
cgecore/cgefinder.py
cgecore/input/__init__.py
cgecore/input/check_input_files.py
cgecore/input/config.py
cgecore/input/handling_args.py
cgecore/input/markdown_documents/__init__.py
cgecore/input/markdown_documents/amr_abbreviations.md
cgecore/input/markdown_documents/environment_variables.md
cgecore/input/markdown_documents/species_abbreviations.md
cgecore/input/output/__init__.py
cgecore/input/output/exceptions.py
cgecore/input/output/gene_result.py
cgecore/input/output/orderedset.py
cgecore/input/output/phenotype_result.py
cgecore/input/output/seq_variation_result.py
cgecore/input/output/std_results.py
cgecore/input/output/table.py
cgecore/input/phenotype2genotype/__init__.py
cgecore-2.0.1.dist-info/RECORD
