Metadata-Version: 2.1
Name: cgecore
Version: 2.0.1
Summary: Modules used throughout the tools developed and maintained by the Center for Genomic Epidemiology (CGE).
Author-Email: Center for Genomic Epidemiology <food-cgehelp@dtu.dk>
License: Apache-2.0
Requires-Python: >=3.10
Requires-Dist: python-dateutil>=2.8.2
Requires-Dist: GitPython>=3.1.40
Requires-Dist: numpy>=1.26.2
Requires-Dist: pandas>=2.1.4
Requires-Dist: biopython>=1.85
